reasonable-0.2.6.dist-info/METADATA
reasonable-0.2.6.dist-info/WHEEL
reasonable/__init__.py
reasonable/reasonable.abi3.so
reasonable-0.2.6.dist-info/RECORD
