Metadata-Version: 2.1
Name: reasonable
Version: 0.2.6
Summary: An OWL 2 RL reasoner with reasonable performance
Home-Page: https://brickschema.org/
Author: Gabe Fierro <gtfierro@mines.edu>
Author-email: Gabe Fierro <gtfierro@mines.edu>
Project-URL: Source Code, https://github.com/gtfierro/reasonable
